paper_color/__init__.py
paper_color/paper_color.py
paper_color/transfer_color.py
paper_color-0.0.3.dist-info/LICENSE
paper_color-0.0.3.dist-info/METADATA
paper_color-0.0.3.dist-info/WHEEL
paper_color-0.0.3.dist-info/top_level.txt
paper_color-0.0.3.dist-info/RECORD
