Metadata-Version: 2.1
Name: paper-color
Version: 0.0.3
Summary: Get colors easily
Home-page: https://github.com/nlply
Author: Yang Liu
Author-email: lauyon@tju.edu.cn
License: UNKNOWN
Platform: UNKNOWN
Classifier: Programming Language :: Python :: 3
Classifier: License :: OSI Approved :: MIT License
Classifier: Operating System :: OS Independent
License-File: LICENSE
